django_command_monitor/__init__.py
django_command_monitor/monitor.py
django_command_monitor-0.1.14.dist-info/METADATA
django_command_monitor-0.1.14.dist-info/RECORD
django_command_monitor-0.1.14.dist-info/WHEEL
django_command_monitor-0.1.14.dist-info/top_level.txt
