Metadata-Version: 2.1
Name: django-command-monitor
Version: 0.1.14
Summary: A toolset for monitoring django commands through FireBase.
Home-page: https://github.com/Orfium/django-command-monitoring
Author: Konstantinos Siaterlis
Author-email: siaterliskonsta@gmail.com
License: LICENSE
Platform: UNKNOWN
Requires-Dist: django (>=1.11)
Requires-Dist: python-firebase
